{
    "gridincx": 1.0,
    "gridincy": 1.0,
    "lines": [
        {
            "angle": 0.0,
            "points": [
                {
                    "x": 0.0,
                    "y": 1.0
                },
                {
                    "x": 0.0,
                    "y": 0.0
                }
            ],
            "tx": 1.0,
            "ty": 0.0
        },
        {
            "angle": 0.0,
            "points": [
                {
                    "x": 0.0,
                    "y": 0.0
                },
                {
                    "x": 0.5,
                    "y": 0.0
                }
            ],
            "tx": 0.5,
            "ty": 1.0
        },
        {
            "angle": 0.0,
            "points": [
                {
                    "x": 0.5,
                    "y": 0.0
                },
                {
                    "x": 1.0,
                    "y": 0.0
                }
            ],
            "tx": -0.5,
            "ty": 1.0
        }
    ],
    "rotdiv": 1,
    "sequence": 0,
    "shiftx": 0.5,
    "shifty": 0.0
}
